goodgleif/__init__.py
goodgleif/canonicalname.py
goodgleif/companymatcher.py
goodgleif/loader.py
goodgleif/paths.py
goodgleif/whereami.py
goodgleif/config/__init__.py
goodgleif/config/abbreviation_standardizations.yaml
goodgleif/config/classification_flags.yaml
goodgleif/data/__init__.py
goodgleif/data/gleif_aerospace_defense.parquet
goodgleif/data/gleif_automotive.parquet
goodgleif/data/gleif_automotive_transportation.parquet
goodgleif/data/gleif_chemical_catalytic.parquet
goodgleif/data/gleif_classified_manifest.txt
goodgleif/data/gleif_clean_tech_renewables.parquet
goodgleif/data/gleif_construction_infrastructure.parquet
goodgleif/data/gleif_consumer_goods_appliances.parquet
goodgleif/data/gleif_electronics_semiconductors.parquet
goodgleif/data/gleif_energy_power.parquet
goodgleif/data/gleif_healthcare_medical_devices.parquet
goodgleif/data/gleif_industrial_machinery.parquet
goodgleif/data/gleif_jewelry_investment_coinage.parquet
goodgleif/data/gleif_manufacturing.parquet
goodgleif/data/gleif_maritime_rail.parquet
goodgleif/data/gleif_metals_and_mining.parquet
goodgleif/data/gleif_mining.parquet
goodgleif/data/gleif_oil_gas_petrochemicals.parquet
goodgleif/data/gleif_recycling_circular_economy.parquet
goodgleif/data/gleif_retail_consumer.parquet
goodgleif/data/gleif_technology.parquet
goodgleif/data/gleif_transportation.parquet
goodgleif/data/seed/.gitkeep
goodgleif/examples/__init__.py
goodgleif/examples/basic_matching_example.py
goodgleif/examples/comprehensive_example.py
goodgleif/examples/exchange_matching_example.py
goodgleif/examples/lei_extraction_example.py
goodgleif/examples/matching_strategies_example.py
goodgleif/examples/run_all_examples.py
goodgleif/examples/score_thresholds_example.py
goodgleif/examples/simple_usage_example.py
goodgleif/exchanges/__init__.py
goodgleif/exchanges/asx.py
goodgleif/exchanges/base.py
goodgleif/exchanges/lse.py
goodgleif/exchanges/template.py
goodgleif/exchanges/tsx.py
goodgleif-0.5.4.dist-info/licenses/LICENSE
goodgleif-0.5.4.dist-info/METADATA
goodgleif-0.5.4.dist-info/WHEEL
goodgleif-0.5.4.dist-info/entry_points.txt
goodgleif-0.5.4.dist-info/top_level.txt
goodgleif-0.5.4.dist-info/RECORD
