Metadata-Version: 2.4
Name: goodgleif
Version: 0.5.4
Summary: Lightweight tools for working with GLEIF LEI data: preprocess, load, fuzzy query.
Author: Peter Cotton
License: MIT License
Requires-Python: >=3.10
License-File: LICENSE
Requires-Dist: pandas>=2.1
Requires-Dist: pyarrow>=14.0
Requires-Dist: rapidfuzz>=3.6
Requires-Dist: platformdirs>=4.2
Requires-Dist: pyyaml>=6.0.1
Requires-Dist: requests>=2.25.0
Provides-Extra: polars
Requires-Dist: polars>=1.8; extra == "polars"
Provides-Extra: dev
Requires-Dist: pytest>=7.4; extra == "dev"
Requires-Dist: ruff>=0.5.0; extra == "dev"
Dynamic: license-file
Dynamic: requires-python
